LICENSE.txt
MANIFEST.in
README.md
setup.py
snipsroku/__init__.py
snipsroku/snipsroku.py
snipsroku.egg-info/PKG-INFO
snipsroku.egg-info/SOURCES.txt
snipsroku.egg-info/dependency_links.txt
snipsroku.egg-info/requires.txt
snipsroku.egg-info/top_level.txt