Metadata-Version: 1.0
Name: snipsroku
Version: 0.1.0
Summary: Roku skill for Snips
Home-page: UNKNOWN
Author: Snips Labs
Author-email: support@snips.ai
License: MIT
Keywords: snips,roku
Platform: UNKNOWN
